feature_implementer-0.1.8.dist-info/licenses/LICENSE
feature_implementer_core/app.py
feature_implementer_core/cli.py
feature_implementer_core/config.py
feature_implementer_core/database.py
feature_implementer_core/feature_implementation_template.md
feature_implementer_core/file_utils.py
feature_implementer_core/prompt_generator.py
feature_implementer_core/static/css/style.css
feature_implementer_core/static/css/base/reset.css
feature_implementer_core/static/css/base/variables.css
feature_implementer_core/static/css/components/buttons.css
feature_implementer_core/static/css/components/cards.css
feature_implementer_core/static/css/components/file-explorer.css
feature_implementer_core/static/css/components/file-preview.css
feature_implementer_core/static/css/components/forms.css
feature_implementer_core/static/css/components/modal.css
feature_implementer_core/static/css/layout/layout.css
feature_implementer_core/static/img/favicon.ico
feature_implementer_core/static/img/favicon.png
feature_implementer_core/static/js/file_explorer.js
feature_implementer_core/static/js/form_handler.js
feature_implementer_core/static/js/modal_utils.js
feature_implementer_core/static/js/preset_handler.js
feature_implementer_core/static/js/theme_toggle.js
feature_implementer_core/static/js/tutorial.js
feature_implementer_core/static/js/ui_utils.js
feature_implementer_core/templates/base.html
feature_implementer_core/templates/index.html
feature_implementer_core/templates/macros.html
feature_implementer_core/templates/result.html
feature_implementer_core/templates/template_manager.html
feature_implementer-0.1.8.dist-info/METADATA
feature_implementer-0.1.8.dist-info/WHEEL
feature_implementer-0.1.8.dist-info/entry_points.txt
feature_implementer-0.1.8.dist-info/top_level.txt
feature_implementer-0.1.8.dist-info/RECORD
