Metadata-Version: 2.4
Name: feature-implementer
Version: 0.1.8
Summary: A tool to help implement features and create specific prompts.
Author-email: Paul Wenner <paul.wenner@crateflow.ai>
Project-URL: Homepage, https://github.com/paulwenner/feature-implementer
Keywords: llm,feature,prompt,implementation,ai,context,cli,web,feature-implement,template
Classifier: Programming Language :: Python :: 3
Classifier: License :: OSI Approved :: MIT License
Classifier: Operating System :: OS Independent
Requires-Python: >=3.8
License-File: LICENSE
Requires-Dist: Jinja2>=3.1
Requires-Dist: Werkzeug>=2.3
Requires-Dist: MarkupSafe>=2.1
Requires-Dist: itsdangerous>=2.1
Requires-Dist: click>=8.1
Requires-Dist: Flask>=2.0
Requires-Dist: gunicorn>=20.1
Requires-Dist: tiktoken>=0.5
Dynamic: license-file
